logging_discord/__init__.py
logging_discord/default.py
logging_discord/dynaconf_config.py
logging_discord/send_discord.py
logging_discord-0.2.2.dist-info/METADATA
logging_discord-0.2.2.dist-info/WHEEL
logging_discord-0.2.2.dist-info/LICENSE
logging_discord-0.2.2.dist-info/RECORD
