Metadata-Version: 2.1
Name: logging-discord
Version: 0.2.2
Summary: The Logging Discord is a tool that simplifies the logging of error messages to a Discord channel. It allows you to send error messages with custom information, including a traceback and specific messages
License: MIT
Author: bruno_brown
Author-email: brunobrown.86@gmail.com
Requires-Python: >=3.10,<4.0
Classifier: Development Status :: 5 - Production/Stable
Classifier: Intended Audience :: Developers
Classifier: License :: OSI Approved :: MIT License
Classifier: Natural Language :: English
Classifier: Natural Language :: Portuguese (Brazilian)
Classifier: Operating System :: OS Independent
Classifier: Programming Language :: Python :: 3
Classifier: Programming Language :: Python :: 3.10
Classifier: Programming Language :: Python :: 3.11
Classifier: Programming Language :: Python :: 3.10
Classifier: Programming Language :: Python :: 3.11
Classifier: Topic :: Software Development :: Debuggers
Requires-Dist: config (>=0.5.1,<0.6.0)
Requires-Dist: dynaconf (>=3.2.3,<4.0.0)
Requires-Dist: httpx (>=0.25.0,<0.26.0)
Project-URL: Bug Tracker, https://github.com/brunobrown/logging-discord/issues
Project-URL: Documentation, https://logging-discord.readthedocs.io/en/latest/
Project-URL: Donate, https://logging-discord.readthedocs.io/en/latest/#support-the-project
Project-URL: GitHub, https://github.com/brunobrown/logging-discord
